fanstore/__init__.py
fanstore/comm.py
fanstore/fanstore.py
fanstore/topology.py
fanstore-0.0.1.dist-info/METADATA
fanstore-0.0.1.dist-info/RECORD
fanstore-0.0.1.dist-info/WHEEL
fanstore-0.0.1.dist-info/top_level.txt
