Metadata-Version: 2.1
Name: fanstore
Version: 0.0.1
Summary: Fanstore gathers local storage space in computer clusters to enable distirbuted neural networks training with larger datasets
Home-page: https://github.com/zhaozhang/fanstore
Author: Zhao Zhang, Lei Huang, Niall Gaffney
Author-email: zzhang@tacc.utexas.edu
License: UNKNOWN
Platform: UNKNOWN
Classifier: Programming Language :: Python :: 3
Classifier: License :: OSI Approved :: MIT License
Classifier: Operating System :: OS Independent
